steel_helper/__init__.py
steel_helper/__main__.py
steel_helper/aisc-shapes-14.xlsx
steel_helper/cli.py
steel_helper/members.py
steel_helper/tension_members.py
steel_helper-0.1.15.dist-info/AUTHORS.rst
steel_helper-0.1.15.dist-info/LICENSE
steel_helper-0.1.15.dist-info/METADATA
steel_helper-0.1.15.dist-info/WHEEL
steel_helper-0.1.15.dist-info/entry_points.txt
steel_helper-0.1.15.dist-info/top_level.txt
steel_helper-0.1.15.dist-info/RECORD
