Metadata-Version: 2.1
Name: steel-helper
Version: 0.1.15
Summary: Python module to help calculate requirements for design of steel structures
Home-page: https://github.com/Denvernoell/steel_helper
Author: Denver Noell
Author-email: denvernoell@gmail.com
License: LGPL-3.0-or-later
Project-URL: Documentation, https://steel-helper.readthedocs.io/
Project-URL: Changelog, https://steel-helper.readthedocs.io/en/latest/changelog.html
Project-URL: Issue Tracker, https://github.com/Denvernoell/steel_helper/issues
Platform: UNKNOWN
Requires-Python: >=3.6
Requires-Dist: pint
